backports.range-3.3.1-py2.7-nspkg.pth
backports/range/LICENSE.txt
backports/range/README.rst
backports/range/__init__.py
backports/range/cyrange_iterator.so
backports/range/pyrange.py
backports/range/pyrange_iterator.py
backports.range-3.3.1.dist-info/DESCRIPTION.rst
backports.range-3.3.1.dist-info/METADATA
backports.range-3.3.1.dist-info/RECORD
backports.range-3.3.1.dist-info/WHEEL
backports.range-3.3.1.dist-info/metadata.json
backports.range-3.3.1.dist-info/namespace_packages.txt
backports.range-3.3.1.dist-info/top_level.txt
